{"CODIGO":"196994","NRO":"1405","RAZON_SOCIAL":"VARGAS ALBORNOZ JORGE LUIS","DOMICILIO_FISCAL":"INDEPROPYME- Mza. M\u00b4 Lte. 01 - ANCON","DISTRITO_DOMICILIO_FISCAL":"ANCON","CODIGO2":"0000008474","ZONA":"SECTOR 5","DOM_PREDIAL":"INDEPROPYME INDEPROPYME Mza. M\u00b4 Lte. 1","IP":"43.57","ARB":"287.05","EMISION":"2.96","TOTAL":"333.58","AUX":"","adicional":{"mperson":"196994","contacto":"5423404","correo":"","documento":"DNI 46548005","nautova":"21783.94","nimpanu":"43.57","ncosemi":"2.96","mhresum_dj":"275277"},"hr_predios":{"8474":{"mperson":"196994","pred":"1","codpredio":"8474","sectorpredio":"ZONA 5","grupourbano":"INDEPROPYME","nombrevia":"INDEPROPYME","direccion":"Mz. MA' Lte. 1","vdirpre":"INDEPROPYME","nporcen":"100","nvalpre":"21783.94","nestado":"1","afecto":"21783.94","mviadis":"125","tipovia":"","tipogrupohab":"OTROS","pu_predio":{"pred":"1","mperson":"196994","codpredio":"8474","usogen":"COMERCIO \/ RESTAURANTE,CHIFA,POLLERIA Y SIMILARES","condicion":"PROPIETARIO UNICO","estadocons":"EN CONSTRUCCION","tipopredio":"PREDIO INDEPENDIENTE","regimen":"AFECTO"},"pu_predio2":{"mperson":"196994","mpredio":"8474","nterren":"300","narecom":"0","narance":"55","nvalpis":"5283.94","nvalins":"0","nvalter":"16500"},"pu_niveles":{"1":{"pi":"1","mperson":"196994","mpredio":"8474","carater":"DCH","estconser":"2","materpredo":"2","clasif":"4","nantigu":"11","narecon":"9","nvaluni":"733.88","nincrem":"0","npordep":"20","ndepred":"146.78","valunideprep":"587.1","nvalpis":"5283.94","cnumpis":"01PI"}},"hla_tasas":{"mperson":"196994","mpredio":"8474","vtippar":"LEJOS DE AREAS VERDES","nfrente":"11.09","cidzona":"5","nbarridanu":"0","nparqueanu":"87.23","nrecoleanu":"8.82","nserenaanu":"191"},"hla_cuotas":{"cidpers":"196994","cidpred":"8474","bc":"0","rs":"1.47","pj":"14.53","sr":"31.83"}}},"valorafectototal":21783.94,"hlp_npre":{"mperson":"196994","nro_predios":"1"}}