{"CODIGO":"261464","NRO":"1453","RAZON_SOCIAL":"FALCON BLAS TANIA MARGOT","DOMICILIO_FISCAL":"AAHH LADERAS DE CARLOS MANUEL COX- Mza. C Lte. 01 - ANCON","DISTRITO_DOMICILIO_FISCAL":"ANCON","CODIGO2":"0000030289","ZONA":"SECTOR 5","DOM_PREDIAL":"AAHH LADERAS DE CARLOS MANUEL COX AAHH LADERAS DE CARLOS MANUEL COX Mza. C Lte. 01","IP":"32.1","ARB":"0","EMISION":"2.96","TOTAL":"35.06","AUX":"","adicional":{"mperson":"261464","contacto":"","correo":"","documento":"DNI 41791979","nautova":"13850.1","nimpanu":"32.1","ncosemi":"2.96","mhresum_dj":"282225"},"hr_predios":{"30289":{"mperson":"261464","pred":"1","codpredio":"30289","sectorpredio":"ZONA 5","grupourbano":"AAHH LADERAS DE CARLOS MANUEL COX","nombrevia":"AAHH LADERAS DE CARLOS MANUEL COX","direccion":"Mz. C Lte. 01","vdirpre":"OTROS AAHH LADERAS DE CARLOS MANUEL COX - OTROS AAHH LADERAS DE CARLOS MANUEL COX        C 01","nporcen":"100","nvalpre":"13850.1","nestado":"1","afecto":"13850.1","mviadis":"311","tipovia":"OTROS","tipogrupohab":"OTROS","pu_predio":{"pred":"1","mperson":"261464","codpredio":"30289","usogen":"OTROS","condicion":"POSEEDOR O TENEDOR","estadocons":"TERMINADO","tipopredio":"PREDIO INDEPENDIENTE","regimen":"AFECTO"},"pu_predio2":{"mperson":"261464","mpredio":"30289","nterren":"139.94","narecom":"0","narance":"46","nvalpis":"7412.86","nvalins":"0","nvalter":"6437.24"},"pu_niveles":{"1":{"pi":"1","mperson":"261464","mpredio":"30289","carater":"FFH","estconser":"3","materpredo":"3","clasif":"1","nantigu":"10","narecon":"40","nvaluni":"285.11","nincrem":"0","npordep":"35","ndepred":"99.79","valunideprep":"185.32","nvalpis":"7412.86","cnumpis":"01PI"}},"hla_tasas":{"mperson":"261464","mpredio":"30289","vtippar":"SIN AREAS VERDES","nfrente":"8","cidzona":"5","nbarridanu":"0","nparqueanu":"0","nrecoleanu":"0","nserenaanu":"0"}}},"valorafectototal":13850.1,"hlp_npre":{"mperson":"261464","nro_predios":"1"}}