{"CODIGO":"263752","NRO":"156","RAZON_SOCIAL":"CAJUSOL VILLALOBOS SOLANSH","DOMICILIO_FISCAL":"AAHH VIRGEN DE LAS MERCEDES- Mza. A26 Lte. 01 - ANCON","DISTRITO_DOMICILIO_FISCAL":"ANCON","CODIGO2":"0000015539","ZONA":"SECTOR 5","DOM_PREDIAL":"AAHH VIRGEN DE LAS MERCEDES AAHH VIRGEN DE LAS MERCEDES Mza. A26 Lte. 01","IP":"50.84","ARB":"91.63","EMISION":"2.96","TOTAL":"145.43","AUX":"","adicional":{"mperson":"263752","contacto":"988332540","correo":"","documento":"DNI 75922494","nautova":"50836.44","nimpanu":"50.84","ncosemi":"2.96","mhresum_dj":"298173"},"hr_predios":{"15539":{"mperson":"263752","pred":"1","codpredio":"15539","sectorpredio":"ZONA 5","grupourbano":"AAHH VIRGEN DE LAS MERCEDES","nombrevia":"AAHH VIRGEN DE LAS MERCEDES","direccion":"Mz. A26 Lte. 01","vdirpre":"AA HH  VIRGEN DE LAS MERCEDES","nporcen":"50","nvalpre":"50836.44","nestado":"1","afecto":"25418.22","mviadis":"320","tipovia":"OTROS","tipogrupohab":"OTROS","pu_predio":{"pred":"1","mperson":"263752","codpredio":"15539","usogen":"CASA HABITACION","condicion":"CONDOMINIO","estadocons":"EN CONSTRUCCION","tipopredio":"PREDIO INDEPENDIENTE","regimen":"AFECTO"},"pu_predio2":{"mperson":"263752","mpredio":"15539","nterren":"120","narecom":"0","narance":"46","nvalpis":"45316.44","nvalins":"0","nvalter":"5520"},"pu_niveles":{"1":{"pi":"1","mperson":"263752","mpredio":"15539","carater":"CCF","estconser":"2","materpredo":"2","clasif":"1","nantigu":"3","narecon":"60","nvaluni":"820.95","nincrem":"0","npordep":"8","ndepred":"65.68","valunideprep":"755.27","nvalpis":"45316.44","cnumpis":"01PI"}},"hla_tasas":{"mperson":"263752","mpredio":"15539","vtippar":"LEJOS DE AREAS VERDES","nfrente":"8","cidzona":"5","nbarridanu":"0","nparqueanu":"43.61","nrecoleanu":"0","nserenaanu":"48.02"},"hla_cuotas":{"cidpers":"263752","cidpred":"15539","bc":"0","rs":"0","pj":"7.26","sr":"8"}}},"valorafectototal":25418.22,"hlp_npre":{"mperson":"263752","nro_predios":"1"}}