{"CODIGO":"200313","NRO":"1706","RAZON_SOCIAL":"RAMOS ABARCA ADELA PILAR","DOMICILIO_FISCAL":"INDEPROPYME- Mza. P Lte. 22 - ANCON","DISTRITO_DOMICILIO_FISCAL":"ANCON","CODIGO2":"0000009052","ZONA":"SECTOR 5","DOM_PREDIAL":"INDEPROPYME INDEPROPYME Mza. P Lte. 22","IP":"34.58","ARB":"287.05","EMISION":"2.96","TOTAL":"324.59","AUX":"","adicional":{"mperson":"200313","contacto":"45285678 931318564","correo":"","documento":"DNI 40885912","nautova":"17291.94","nimpanu":"34.58","ncosemi":"2.96","mhresum_dj":"280157"},"hr_predios":{"9052":{"mperson":"200313","pred":"1","codpredio":"9052","sectorpredio":"ZONA 5","grupourbano":"INDEPROPYME","nombrevia":"INDEPROPYME","direccion":"Mz. P Lte. 22","vdirpre":"INDEPROPYME","nporcen":"100","nvalpre":"17291.94","nestado":"1","afecto":"17291.94","mviadis":"125","tipovia":"","tipogrupohab":"OTROS","pu_predio":{"pred":"1","mperson":"200313","codpredio":"9052","usogen":"COMERCIO \/ RESTAURANTE,CHIFA,POLLERIA Y SIMILARES","condicion":"PROPIETARIO UNICO","estadocons":"EN CONSTRUCCION","tipopredio":"PREDIO INDEPENDIENTE","regimen":"AFECTO"},"pu_predio2":{"mperson":"200313","mpredio":"9052","nterren":"250","narecom":"0","narance":"55","nvalpis":"3541.94","nvalins":"0","nvalter":"13750"},"pu_niveles":{"1":{"pi":"1","mperson":"200313","mpredio":"9052","carater":"DFH","estconser":"2","materpredo":"2","clasif":"4","nantigu":"10","narecon":"9","nvaluni":"468.51","nincrem":"0","npordep":"16","ndepred":"74.96","valunideprep":"393.55","nvalpis":"3541.94","cnumpis":"01PI"}},"hla_tasas":{"mperson":"200313","mpredio":"9052","vtippar":"LEJOS DE AREAS VERDES","nfrente":"10.12","cidzona":"5","nbarridanu":"0","nparqueanu":"87.23","nrecoleanu":"8.82","nserenaanu":"191"},"hla_cuotas":{"cidpers":"200313","cidpred":"9052","bc":"0","rs":"1.47","pj":"14.53","sr":"31.83"}}},"valorafectototal":17291.94,"hlp_npre":{"mperson":"200313","nro_predios":"1"}}