{"CODIGO":"673","NRO":"1732","RAZON_SOCIAL":"CASTILLO LETHAM GUILLERMO","DOMICILIO_FISCAL":"2 DE MAYO- Nro. 244 Dpt. D - ANCON","DISTRITO_DOMICILIO_FISCAL":"ANCON","CODIGO2":"0000000523","ZONA":"SECTOR 2","DOM_PREDIAL":"Ca 2 DE MAYO Ca 2 DE MAYO Nro. 244 Dpt. D","IP":"266.38","ARB":"341.09","EMISION":"2.96","TOTAL":"610.43","AUX":"","adicional":{"mperson":"673","contacto":"","correo":"","documento":"DNI ","nautova":"97897","nimpanu":"266.38","ncosemi":"2.96","mhresum_dj":"292104"},"hr_predios":{"523":{"mperson":"673","pred":"1","codpredio":"523","sectorpredio":"ZONA 2","grupourbano":"Ca 2 DE MAYO","nombrevia":"Ca 2 DE MAYO","direccion":"Nro 244  Dpto. D","vdirpre":"CA  2 DE MAYO","nporcen":"100","nvalpre":"97897","nestado":"1","afecto":"97897","mviadis":"220","tipovia":"OTROS","tipogrupohab":"OTROS","pu_predio":{"pred":"1","mperson":"673","codpredio":"523","usogen":"CASA HABITACION","condicion":"PROPIETARIO UNICO","estadocons":"TERMINADO","tipopredio":"PREDIO INDEPENDIENTE","regimen":"AFECTO"},"pu_predio2":{"mperson":"673","mpredio":"523","nterren":"64","narecom":"0","narance":"471","nvalpis":"67753","nvalins":"0","nvalter":"30144"},"pu_niveles":{"1":{"pi":"1","mperson":"673","mpredio":"523","carater":"CCF","estconser":"3","materpredo":"1","clasif":"1","nantigu":"63","narecon":"131","nvaluni":"820.95","nincrem":"0","npordep":"37","ndepred":"303.75","valunideprep":"517.2","nvalpis":"67753","cnumpis":"01PI"}},"hla_tasas":{"mperson":"673","mpredio":"523","vtippar":"LEJOS DE AREAS VERDES","nfrente":"5.12","cidzona":"2","nbarridanu":"86.44","nparqueanu":"87.23","nrecoleanu":"72.22","nserenaanu":"95.2"},"hla_cuotas":{"cidpers":"673","cidpred":"523","bc":"14.4","rs":"12.03","pj":"14.53","sr":"15.86"}}},"valorafectototal":97897,"hlp_npre":{"mperson":"673","nro_predios":"1"}}