{"CODIGO":"196924","NRO":"1772","RAZON_SOCIAL":"HERNANDEZ TERRONES EULER DANILO","DOMICILIO_FISCAL":"INDEPROPYME- Mza. B2 Lte. 9 - ANCON","DISTRITO_DOMICILIO_FISCAL":"ANCON","CODIGO2":"0000008402","ZONA":"SECTOR 5","DOM_PREDIAL":"INDEPROPYME INDEPROPYME Mza. B2 Lte. 9","IP":"41.31","ARB":"288.02","EMISION":"2.96","TOTAL":"332.29","AUX":"","adicional":{"mperson":"196924","contacto":"95209404","correo":"","documento":"DNI 42531546","nautova":"20656.24","nimpanu":"41.31","ncosemi":"2.96","mhresum_dj":"277677"},"hr_predios":{"8402":{"mperson":"196924","pred":"1","codpredio":"8402","sectorpredio":"ZONA 5","grupourbano":"INDEPROPYME","nombrevia":"INDEPROPYME","direccion":"Mz. B2 Lte. 9","vdirpre":"INDEPROPYME","nporcen":"100","nvalpre":"20656.24","nestado":"1","afecto":"20656.24","mviadis":"125","tipovia":"","tipogrupohab":"OTROS","pu_predio":{"pred":"1","mperson":"196924","codpredio":"8402","usogen":"COMERCIO \/ RESTAURANTE,CHIFA,POLLERIA Y SIMILARES","condicion":"PROPIETARIO UNICO","estadocons":"EN CONSTRUCCION","tipopredio":"PREDIO INDEPENDIENTE","regimen":"AFECTO"},"pu_predio2":{"mperson":"196924","mpredio":"8402","nterren":"300","narecom":"0","narance":"55","nvalpis":"4156.24","nvalins":"0","nvalter":"16500"},"pu_niveles":{"1":{"pi":"1","mperson":"196924","mpredio":"8402","carater":"DFG","estconser":"2","materpredo":"2","clasif":"4","nantigu":"10","narecon":"10","nvaluni":"494.79","nincrem":"0","npordep":"16","ndepred":"79.17","valunideprep":"415.62","nvalpis":"4156.24","cnumpis":"01PI"}},"hla_tasas":{"mperson":"196924","mpredio":"8402","vtippar":"LEJOS DE AREAS VERDES","nfrente":"11.09","cidzona":"5","nbarridanu":"0","nparqueanu":"87.23","nrecoleanu":"9.79","nserenaanu":"191"},"hla_cuotas":{"cidpers":"196924","cidpred":"8402","bc":"0","rs":"1.63","pj":"14.53","sr":"31.83"}}},"valorafectototal":20656.24,"hlp_npre":{"mperson":"196924","nro_predios":"1"}}