{"CODIGO":"257531","NRO":"1881","RAZON_SOCIAL":"SOLIS TORRES ANGEL MARIO","DOMICILIO_FISCAL":"INDEPROPYME- Mza. \u00d1 Lte. 29 - ANCON","DISTRITO_DOMICILIO_FISCAL":"ANCON","CODIGO2":"0000026605","ZONA":"SECTOR 5","DOM_PREDIAL":"INDEPROPYME INDEPROPYME Mza. \u00d1 Lte. 29","IP":"125.32","ARB":"0","EMISION":"2.96","TOTAL":"128.28","AUX":"","adicional":{"mperson":"257531","contacto":"981474314","correo":"","documento":"DNI 31682323","nautova":"62660.38","nimpanu":"125.32","ncosemi":"2.96","mhresum_dj":"277604"},"hr_predios":{"26605":{"mperson":"257531","pred":"1","codpredio":"26605","sectorpredio":"ZONA 5","grupourbano":"INDEPROPYME","nombrevia":"INDEPROPYME","direccion":"Mz. \u00d1 Lte. 29","vdirpre":"OTROS INDEPROPYME -  INDEPROPYME        \u00d1 29","nporcen":"100","nvalpre":"62660.38","nestado":"1","afecto":"62660.38","mviadis":"125","tipovia":"","tipogrupohab":"OTROS","pu_predio":{"pred":"1","mperson":"257531","codpredio":"26605","usogen":"OTROS","condicion":"POSEEDOR O TENEDOR","estadocons":"TERMINADO","tipopredio":"PREDIO INDEPENDIENTE","regimen":"AFECTO"},"pu_predio2":{"mperson":"257531","mpredio":"26605","nterren":"300","narecom":"0","narance":"55","nvalpis":"46160.38","nvalins":"0","nvalter":"16500"},"pu_niveles":{"1":{"pi":"1","mperson":"257531","mpredio":"26605","carater":"DDG","estconser":"2","materpredo":"2","clasif":"1","nantigu":"6","narecon":"80","nvaluni":"648.32","nincrem":"0","npordep":"11","ndepred":"71.32","valunideprep":"577","nvalpis":"46160.38","cnumpis":"01PI"}},"hla_tasas":{"mperson":"257531","mpredio":"26605","vtippar":"SIN AREAS VERDES","nfrente":"10","cidzona":"5","nbarridanu":"0","nparqueanu":"0","nrecoleanu":"0","nserenaanu":"0"}}},"valorafectototal":62660.38,"hlp_npre":{"mperson":"257531","nro_predios":"1"}}