{"CODIGO":"196415","NRO":"473","RAZON_SOCIAL":"ZEVALLOS LEVANO JOSE MANUEL","DOMICILIO_FISCAL":"INDEPROPYME- Mza. M\u00b4 Lte. 12 - ANCON","DISTRITO_DOMICILIO_FISCAL":"ANCON","CODIGO2":"0000004890","ZONA":"SECTOR 5","DOM_PREDIAL":"ASOCIACION PARQUE INDUSTRIAL DE ANC\u00d3N Av LOS RADARES Mza. J2 Lte. 05","IP":"6070.23","ARB":"5876.65","EMISION":"3.94","TOTAL":"11950.82","AUX":"","adicional":{"mperson":"196415","contacto":"66423596 966423596","correo":"","documento":"DNI 45826325","nautova":"767522.7585","nimpanu":"6070.23","ncosemi":"3.94","mhresum_dj":"295867"},"hr_predios":{"4890":{"mperson":"196415","pred":"1","codpredio":"4890","sectorpredio":"ZONA 5","grupourbano":"ASOCIACION PARQUE INDUSTRIAL DE ANC\u00d3N","nombrevia":"Av LOS RADARES","direccion":"Mz. J2 Lte. 05","vdirpre":"ACOMPIA (AV  LOS RADARES)","nporcen":"100","nvalpre":"742086.8485","nestado":"1","afecto":"742086.8485","mviadis":"102","tipovia":"OTROS","tipogrupohab":"OTROS","pu_predio":{"pred":"1","mperson":"196415","codpredio":"4890","usogen":"INDUSTRIA","condicion":"PROPIETARIO UNICO","estadocons":"EN CONSTRUCCION","tipopredio":"PREDIO INDEPENDIENTE","regimen":"AFECTO"},"pu_predio2":{"mperson":"196415","mpredio":"4890","nterren":"1494.25","narecom":"0","narance":"26","nvalpis":"491461.6","nvalins":"211774.7485","nvalter":"38850.5"},"pu_niveles":{"1":{"pi":"1","mperson":"196415","mpredio":"4890","carater":"CDE","estconser":"2","materpredo":"1","clasif":"4","nantigu":"1","narecon":"700","nvaluni":"739.04","nincrem":"0","npordep":"5","ndepred":"36.95","valunideprep":"702.09","nvalpis":"491461.6","cnumpis":"01PI"}},"hla_tasas":{"mperson":"196415","mpredio":"4890","vtippar":"CERCA A AREAS VERDES","nfrente":"24.74","cidzona":"5","nbarridanu":"0","nparqueanu":"99.36","nrecoleanu":"5231.6","nserenaanu":"362.41"},"hla_cuotas":{"cidpers":"196415","cidpred":"4890","bc":"0","rs":"871.93","pj":"16.56","sr":"60.4"}},"8341":{"mperson":"196415","pred":"2","codpredio":"8341","sectorpredio":"ZONA 5","grupourbano":"INDEPROPYME","nombrevia":"INDEPROPYME","direccion":"Mz. MA' Lte. 12","vdirpre":"INDEPROPYME        MA' 12","nporcen":"100","nvalpre":"25435.91","nestado":"1","afecto":"25435.91","mviadis":"125","tipovia":"","tipogrupohab":"OTROS","pu_predio":{"pred":"2","mperson":"196415","codpredio":"8341","usogen":"CASA HABITACION","condicion":"POSEEDOR O TENEDOR","estadocons":"EN CONSTRUCCION","tipopredio":"PREDIO INDEPENDIENTE","regimen":"AFECTO"},"pu_predio2":{"mperson":"196415","mpredio":"8341","nterren":"300","narecom":"0","narance":"55","nvalpis":"8935.91","nvalins":"0","nvalter":"16500"},"pu_niveles":{"1":{"pi":"1","mperson":"196415","mpredio":"8341","carater":"DFG","estconser":"2","materpredo":"2","clasif":"1","nantigu":"12","narecon":"21","nvaluni":"494.79","nincrem":"0","npordep":"14","ndepred":"69.27","valunideprep":"425.52","nvalpis":"8935.91","cnumpis":"01PI"}},"hla_tasas":{"mperson":"196415","mpredio":"8341","vtippar":"LEJOS DE AREAS VERDES","nfrente":"11.09","cidzona":"5","nbarridanu":"0","nparqueanu":"87.23","nrecoleanu":"0","nserenaanu":"96.05"},"hla_cuotas":{"cidpers":"196415","cidpred":"8341","bc":"0","rs":"0","pj":"14.53","sr":"16"}}},"valorafectototal":767522.7585,"hlp_npre":{"mperson":"196415","nro_predios":"2"}}