{"CODIGO":"19275","NRO":"651","RAZON_SOCIAL":"MENDOZA JUAREZ CARMEN GLADYS","DOMICILIO_FISCAL":"INDEPROPYME- Mza. O Lte. 01-02 - ANCON","DISTRITO_DOMICILIO_FISCAL":"ANCON","CODIGO2":"0000007892","ZONA":"SECTOR 5","DOM_PREDIAL":"INDEPROPYME INDEPROPYME Mza. O Lte. 1 2","IP":"117.47","ARB":"327.24","EMISION":"2.96","TOTAL":"447.67","AUX":"","adicional":{"mperson":"19275","contacto":"20048333","correo":"","documento":"DNI 21416716","nautova":"58735.29","nimpanu":"117.47","ncosemi":"2.96","mhresum_dj":"279811"},"hr_predios":{"7892":{"mperson":"19275","pred":"1","codpredio":"7892","sectorpredio":"ZONA 5","grupourbano":"INDEPROPYME","nombrevia":"INDEPROPYME","direccion":"Mz. O Lte. 1 2","vdirpre":"INDEPROPYME","nporcen":"100","nvalpre":"58735.29","nestado":"1","afecto":"58735.29","mviadis":"125","tipovia":"","tipogrupohab":"OTROS","pu_predio":{"pred":"1","mperson":"19275","codpredio":"7892","usogen":"COMERCIO \/ RESTAURANTE,CHIFA,POLLERIA Y SIMILARES","condicion":"POSEEDOR O TENEDOR","estadocons":"EN CONSTRUCCION","tipopredio":"PREDIO INDEPENDIENTE","regimen":"AFECTO"},"pu_predio2":{"mperson":"19275","mpredio":"7892","nterren":"778.29","narecom":"0","narance":"55","nvalpis":"15929.34","nvalins":"0","nvalter":"42805.95"},"pu_niveles":{"1":{"pi":"1","mperson":"19275","mpredio":"7892","carater":"DFH","estconser":"3","materpredo":"2","clasif":"4","nantigu":"11","narecon":"50","nvaluni":"468.51","nincrem":"0","npordep":"32","ndepred":"149.92","valunideprep":"318.59","nvalpis":"15929.34","cnumpis":"01PI"}},"hla_tasas":{"mperson":"19275","mpredio":"7892","vtippar":"LEJOS DE AREAS VERDES","nfrente":"17.85","cidzona":"5","nbarridanu":"0","nparqueanu":"87.23","nrecoleanu":"49.01","nserenaanu":"191"},"hla_cuotas":{"cidpers":"19275","cidpred":"7892","bc":"0","rs":"8.16","pj":"14.53","sr":"31.83"}}},"valorafectototal":58735.29,"hlp_npre":{"mperson":"19275","nro_predios":"1"}}