{"CODIGO":"263449","NRO":"873","RAZON_SOCIAL":"ESPINO RAMOS MARIA FABIOLA","DOMICILIO_FISCAL":"AV COPACABANA- Mza. 13 Lte. 08 - ANCON","DISTRITO_DOMICILIO_FISCAL":"ANCON","CODIGO2":"0000005372","ZONA":"SECTOR 2","DOM_PREDIAL":"URB MIRAMAR AV COPACABANA Mza. 13 Lte. 08","IP":"477.16","ARB":"418.94","EMISION":"2.96","TOTAL":"899.06","AUX":"","adicional":{"mperson":"263449","contacto":"972305362","correo":"","documento":"DNI 40906564","nautova":"133027.38","nimpanu":"477.16","ncosemi":"2.96","mhresum_dj":"297396"},"hr_predios":{"5372":{"mperson":"263449","pred":"1","codpredio":"5372","sectorpredio":"ZONA 2","grupourbano":"URB MIRAMAR","nombrevia":"AV COPACABANA","direccion":"Mz. 13 Lte. 08","vdirpre":"AV  COPACABANA","nporcen":"100","nvalpre":"133027.38","nestado":"1","afecto":"133027.38","mviadis":"169","tipovia":"OTROS","tipogrupohab":"OTROS","pu_predio":{"pred":"1","mperson":"263449","codpredio":"5372","usogen":"CASA HABITACION","condicion":"PROPIETARIO UNICO","estadocons":"EN CONSTRUCCION","tipopredio":"PREDIO INDEPENDIENTE","regimen":"AFECTO"},"pu_predio2":{"mperson":"263449","mpredio":"5372","nterren":"299.34","narecom":"0","narance":"182","nvalpis":"78547.5","nvalins":"0","nvalter":"54479.88"},"pu_niveles":{"1":{"pi":"1","mperson":"263449","mpredio":"5372","carater":"CCD","estconser":"1","materpredo":"2","clasif":"1","nantigu":"2","narecon":"90","nvaluni":"872.75","nincrem":"0","npordep":"0","ndepred":"0","valunideprep":"872.75","nvalpis":"78547.5","cnumpis":"01PI"}},"hla_tasas":{"mperson":"263449","mpredio":"5372","vtippar":"LEJOS DE AREAS VERDES","nfrente":"11.07","cidzona":"2","nbarridanu":"186.89","nparqueanu":"87.23","nrecoleanu":"49.62","nserenaanu":"95.2"},"hla_cuotas":{"cidpers":"263449","cidpred":"5372","bc":"31.14","rs":"8.27","pj":"14.53","sr":"15.86"}}},"valorafectototal":133027.38,"hlp_npre":{"mperson":"263449","nro_predios":"1"}}