{"CODIGO":"259224","NRO":"96","RAZON_SOCIAL":"JARA SAAVEDRA SEGUNDO JOSE \/ LOPEZ LEZAMA ROSA MARIA","DOMICILIO_FISCAL":"AAHH LA ALAMEDA DE ANCON- Mza. B Lte. 17 - ANCON","DISTRITO_DOMICILIO_FISCAL":"ANCON","CODIGO2":"0000028287","ZONA":"SECTOR 5","DOM_PREDIAL":"AAHH LA ALAMEDA DE ANCON AAHH LA ALAMEDA DE ANCON Mza. B Lte. 17","IP":"32.1","ARB":"183.28","EMISION":"2.96","TOTAL":"218.34","AUX":"","adicional":{"mperson":"259224","contacto":"975560429","correo":"","documento":"DNI 10377059","nautova":"13473.99","nimpanu":"32.1","ncosemi":"2.96","mhresum_dj":"275504"},"hr_predios":{"28287":{"mperson":"259224","pred":"1","codpredio":"28287","sectorpredio":"ZONA 5","grupourbano":"AAHH LA ALAMEDA DE ANCON","nombrevia":"AAHH LA ALAMEDA DE ANCON","direccion":"Mz. B Lte. 17","vdirpre":"OTROS AAHH LA ALAMEDA DE ANCON - OTROS AAHH LA ALAMEDA DE ANCON        B 17","nporcen":"100","nvalpre":"13473.99","nestado":"1","afecto":"13473.99","mviadis":"75","tipovia":"OTROS","tipogrupohab":"OTROS","pu_predio":{"pred":"1","mperson":"259224","codpredio":"28287","usogen":"CASA HABITACION","condicion":"PROPIETARIO UNICO","estadocons":"TERMINADO","tipopredio":"PREDIO INDEPENDIENTE","regimen":"AFECTO"},"pu_predio2":{"mperson":"259224","mpredio":"28287","nterren":"88.4","narecom":"0","narance":"35","nvalpis":"10379.99","nvalins":"0","nvalter":"3094"},"pu_niveles":{"1":{"pi":"1","mperson":"259224","mpredio":"28287","carater":"GDE","estconser":"3","materpredo":"2","clasif":"1","nantigu":"6","narecon":"30","nvaluni":"449.35","nincrem":"0","npordep":"23","ndepred":"103.35","valunideprep":"346","nvalpis":"10379.99","cnumpis":"01PI"}},"hla_tasas":{"mperson":"259224","mpredio":"28287","vtippar":"LEJOS DE AREAS VERDES","nfrente":"6","cidzona":"5","nbarridanu":"0","nparqueanu":"87.23","nrecoleanu":"0","nserenaanu":"96.05"},"hla_cuotas":{"cidpers":"259224","cidpred":"28287","bc":"0","rs":"0","pj":"14.53","sr":"16"}}},"valorafectototal":13473.99,"hlp_npre":{"mperson":"259224","nro_predios":"1"}}